marshmallow_helpers/__init__.py
marshmallow_helpers/enum_field.py
marshmallow_helpers/marsh_schema.py
marshmallow_helpers/model.py
marshmallow_helpers/marshmallow_annotations/__init__.py
marshmallow_helpers/marshmallow_annotations/_compat.py
marshmallow_helpers/marshmallow_annotations/base.py
marshmallow_helpers/marshmallow_annotations/converter.py
marshmallow_helpers/marshmallow_annotations/exceptions.py
marshmallow_helpers/marshmallow_annotations/registry.py
marshmallow_helpers/marshmallow_annotations/scheme.py
marshmallow_helpers/marshmallow_annotations/ext/__init__.py
marshmallow_helpers/marshmallow_annotations/ext/attrs.py
marshmallow_helpers/marshmallow_annotations/ext/namedtuple.py
marshmallow_helpers-0.4.5.dist-info/LICENSE
marshmallow_helpers-0.4.5.dist-info/METADATA
marshmallow_helpers-0.4.5.dist-info/WHEEL
marshmallow_helpers-0.4.5.dist-info/dependency_links.txt
marshmallow_helpers-0.4.5.dist-info/top_level.txt
marshmallow_helpers-0.4.5.dist-info/RECORD
